COPYING
Changelog.txt
MANIFEST.in
README
VERSION
setup.cfg
setup.py
moa/__init__.py
moa/actor.py
moa/args.py
moa/commands.py
moa/exceptions.py
moa/filesets.py
moa/job.py
moa/jobConf.py
moa/logger.py
moa/moajinja.py
moa/script.py
moa/sysConf.py
moa/ui.py
moa/utils.py
moa/version.py
moa.egg-info/PKG-INFO
moa.egg-info/SOURCES.txt
moa.egg-info/dependency_links.txt
moa.egg-info/entry_points.txt
moa.egg-info/not-zip-safe
moa.egg-info/requires.txt
moa.egg-info/top_level.txt
moa/backend/__init__.py
moa/backend/nojob.py
moa/backend/ruff/__init__.py
moa/backend/ruff/base.py
moa/backend/ruff/commands.py
moa/backend/ruff/executor.py
moa/backend/ruff/map.py
moa/backend/ruff/reduce.py
moa/backend/ruff/simple.py
moa/backend/ruff/test.py
moa/cli/__init__.py
moa/cli/main.py
moa/cli/moainit.py
moa/cli/moaprompt.py
moa/cli/moar.py
moa/cli/setstatus.py
moa/data/etc/config
moa/data/etc/profile.d/moa.sh
moa/data/jinja2/command.snippet.rst.jinja2
moa/data/jinja2/plugin.index.rst.jinja2
moa/data/jinja2/plugin.rst.jinja2
moa/data/jinja2/template.help.jinja2
moa/data/jinja2/template.index.rst.jinja2
moa/data/jinja2/template.readme.jinja2
moa/data/jinja2/template.rst.jinja2
moa/data/logo/mao.txt
moa/data/logo/moa.logo.txt
moa/data/templates/abyss_pe.jinja2
moa/data/templates/abyss_pe.moa
moa/data/templates/abyss_se.jinja2
moa/data/templates/abyss_se.moa
moa/data/templates/archroot.jinja2
moa/data/templates/archroot.moa
moa/data/templates/autohagfish.jinja2
moa/data/templates/autohagfish.moa
moa/data/templates/bamextract.jinja2
moa/data/templates/bamextract.moa
moa/data/templates/bdbb.jinja2
moa/data/templates/bdbb.moa
moa/data/templates/bfast_aln.jinja2
moa/data/templates/bfast_aln.moa
moa/data/templates/bfast_db.jinja2
moa/data/templates/bfast_db.moa
moa/data/templates/blast.jinja2
moa/data/templates/blast.moa
moa/data/templates/blastdb.jinja2
moa/data/templates/blastdb.moa
moa/data/templates/bowtie.jinja2
moa/data/templates/bowtie.moa
moa/data/templates/bowtie_pe.finish.jinja2
moa/data/templates/bowtie_pe.jinja2
moa/data/templates/bowtie_pe.moa
moa/data/templates/bowtie_se.jinja2
moa/data/templates/bowtie_se.moa
moa/data/templates/bowtiedb.jinja2
